{
  "0.02h1p8qbflx5": {
    "content": "ho",
    "from": 1506643200000,
    "to": 1506729600000,
    "color": "orange"
  },
  "0.cr5uoi7dq4j": {
    "content": "hæ",
    "from": 1506384000000,
    "to": 1506618757051,
    "color": "green"
  },
  "0.ceeiifax1ql": {
    "content": "ha",
    "from": 1505692800000,
    "to": 1506618757051,
    "color": "brown"
  },
  "0.edz4756s8f8": {
    "content": "ho",
    "from": 1504742400000,
    "to": 1505174400000,
    "color": "red"
  },
  "0.8ly2do89rmb": {
    "content": "hei",
    "from": 1506384000000,
    "to": 1506618757051,
    "color": "blue"
  }
}
